Metadata-Version: 2.1
Name: blmath
Version: 1.2.6
Summary: A collection of math related utilities used by many bits of BodyLabs code
Home-page: https://github.com/bodylabs/blmath
Author: Body Labs
Author-email: alex@bodylabs.com
License: MIT
Platform: UNKNOWN
Classifier: Development Status :: 3 - Alpha
Classifier: Intended Audience :: Developers
Classifier: License :: OSI Approved :: BSD License
Classifier: Operating System :: OS Independent
Classifier: Programming Language :: Python
Requires-Dist: cached-property (>=1.3.0)
Requires-Dist: numpy (>=1.10.1)
Requires-Dist: plumbum (>=1.6.3)
Requires-Dist: scipy (>=0.14.1)
Requires-Dist: scikit-learn (>=0.17.1)
Requires-Dist: baiji (>=2.5.3)
Requires-Dist: baiji-serialization (>=2.0.0)
Requires-Dist: baiji-pod (>=1.0.0)
Requires-Dist: chumpy (>=0.65.5)
